multiskin/__init__.py
multiskin/cape.py
multiskin/cli.py
multiskin/model.py
multiskin/clean/__init__.py
multiskin/clean/clean_skin.py
multiskin/clean/empty_64x64.png
multiskin/clean/skintemplate_masked_alpha.png
tests/__init__.py
tests/test_inference.py
multiskin-1.4.2.dist-info/METADATA
multiskin-1.4.2.dist-info/WHEEL
multiskin-1.4.2.dist-info/RECORD
