Metadata-Version: 2.1
Name: multiskin
Version: 1.4.2
Summary: A small package for Multiskin
Project-URL: Homepage, https://multi.skin
Project-URL: Bug Tracker, https://multi.skin
Author-email: Josh Elgar <joshelgar@gmail.com>
Classifier: Operating System :: OS Independent
Classifier: Programming Language :: Python :: 3.9
Requires-Python: >=3.9
Requires-Dist: alt-profanity-check
Requires-Dist: dataclasses
Requires-Dist: diffusers[torch]
Requires-Dist: huggingface-hub
Requires-Dist: pillow
Requires-Dist: pixelate
Requires-Dist: smartcrop
Requires-Dist: transformers
Requires-Dist: typing
